tensorcv/__init__.py
tensorcv/Classification/__init__.py
tensorcv/Classification/_alexnet.py
tensorcv/Classification/_densenet.py
tensorcv/Classification/_inception.py
tensorcv/Classification/_resnet.py
tensorcv/Classification/_resnetv1b.py
tensorcv/Classification/_resnext.py
tensorcv/Classification/_senet.py
tensorcv/Classification/_squeezenet.py
tensorcv/Classification/_vgg.py
tensorcv/Detection/__init__.py
tensorcv/Segmentation/__init__.py
tensorcv/data/__init__.py
tensorcv/data/_sample.py
tensorcv/data/datasets/__init__.py
tensorcv/data/datasets/_cifar.py
tensorcv/data/datasets/_mnist.py
tensorcv/data/datasets/_mnist_kuzushiji.py
tensorcv/data/datasets/_mnist_tibetan.py
tensorcv/image/__init__.py
tensorcv/image/_image_ops.py
tensorcv-0.2.0.dist-info/METADATA
tensorcv-0.2.0.dist-info/RECORD
tensorcv-0.2.0.dist-info/WHEEL
tensorcv-0.2.0.dist-info/top_level.txt
