Metadata-Version: 2.1
Name: tensorcv
Version: 0.2.0
Summary: tf.Keras implementations of a Deep Learning Toolkit for Computer Vision.
Home-page: https://github.com/Hourout/tensorcv
Author: JinQing Lee
Author-email: hourout@163.com
License: Apache License Version 2.0
Keywords: computer-vision,keras,tf.keras,deep-learning
Platform: UNKNOWN
Classifier: Intended Audience :: Developers
Classifier: Intended Audience :: Education
Classifier: Intended Audience :: Science/Research
Classifier: Topic :: Scientific/Engineering
Classifier: Topic :: Scientific/Engineering :: Artificial Intelligence
Classifier: Topic :: Scientific/Engineering :: Visualization
Classifier: License :: OSI Approved :: Apache Software License
Classifier: Programming Language :: Python :: 3.5
Classifier: Programming Language :: Python :: 3.6
Requires-Dist: pandas
Requires-Dist: numpy
Requires-Dist: imageio
Requires-Dist: tensorflow (>=1.12.0)
